portapy/__init__.py
portapy/flask.py
portapy/parser.py
portapy/utils.py
portapy/compiler/__init__.py
portapy/compiler/template.py
portapy/compiler/angular/__init__.py
portapy/compiler/js/__init__.py
portapy/core/__init__.py
portapy/core/api.py
portapy/core/endpoint.py
portapy/core/mapping.py
portapy/core/model.py
portapy/core/params.py
portapy/core/security.py
portapy/core/types.py
portapy-js/.gitignore
portapy-js/package-lock.json
portapy-js/package.json
portapy-js/tsconfig.json
portapy-js/tslint.json
portapy-js/dist/base.d.ts
portapy-js/dist/base.js
portapy-js/dist/client.d.ts
portapy-js/dist/client.js
portapy-js/dist/http.d.ts
portapy-js/dist/http.js
portapy-js/dist/index.d.ts
portapy-js/dist/index.js
portapy-js/dist/polyfills.d.ts
portapy-js/dist/polyfills.js
portapy-js/node_modules/.package-lock.json
portapy-js/node_modules/.bin/editorconfig
portapy-js/node_modules/.bin/esparse
portapy-js/node_modules/.bin/esvalidate
portapy-js/node_modules/.bin/js-yaml
portapy-js/node_modules/.bin/mkdirp
portapy-js/node_modules/.bin/semver
portapy-js/node_modules/.bin/ts-node
portapy-js/node_modules/.bin/tsc
portapy-js/node_modules/.bin/tsfmt
portapy-js/node_modules/.bin/tslint
portapy-js/node_modules/.bin/tsserver
portapy-js/node_modules/@babel/code-frame/LICENSE
portapy-js/node_modules/@babel/code-frame/README.md
portapy-js/node_modules/@babel/code-frame/package.json
portapy-js/node_modules/@babel/code-frame/lib/index.js
portapy-js/node_modules/@babel/helper-validator-identifier/LICENSE
portapy-js/node_modules/@babel/helper-validator-identifier/README.md
portapy-js/node_modules/@babel/helper-validator-identifier/package.json
portapy-js/node_modules/@babel/helper-validator-identifier/lib/identifier.js
portapy-js/node_modules/@babel/helper-validator-identifier/lib/index.js
portapy-js/node_modules/@babel/helper-validator-identifier/lib/keyword.js
portapy-js/node_modules/@babel/helper-validator-identifier/scripts/generate-identifier-regex.js
portapy-0.0.1.post2.dist-info/LICENSE
portapy-0.0.1.post2.dist-info/METADATA
portapy-0.0.1.post2.dist-info/WHEEL
portapy-0.0.1.post2.dist-info/top_level.txt
portapy-0.0.1.post2.dist-info/RECORD
